sling/__init__.py
sling/arrow.py
sling/bin.py
sling/enum.py
sling/hooks.py
sling/options.py
sling-1.5.5.dist-info/METADATA
sling-1.5.5.dist-info/WHEEL
sling-1.5.5.dist-info/entry_points.txt
sling-1.5.5.dist-info/top_level.txt
sling-1.5.5.dist-info/RECORD
