Metadata-Version: 2.4
Name: sling
Version: 1.5.5
Summary: Slings data from a source to a target
Home-page: https://github.com/slingdata-io/sling-python
Download-URL: https://github.com/slingdata-io/sling-python/archive/master.zip
Author: Sling Data
Author-email: support@slingdata.io
Keywords: sling,etl,elt,extract,load
Classifier: Programming Language :: Python :: 3
Classifier: Intended Audience :: Developers
Classifier: Intended Audience :: Education
Classifier: Intended Audience :: Science/Research
Classifier: Operating System :: MacOS
Classifier: Operating System :: Unix
Classifier: Topic :: Utilities
Provides-Extra: arrow
Requires-Dist: pyarrow; extra == "arrow"
Provides-Extra: recommended
Requires-Dist: pyarrow; extra == "recommended"
Dynamic: author
Dynamic: author-email
Dynamic: classifier
Dynamic: description
Dynamic: description-content-type
Dynamic: download-url
Dynamic: home-page
Dynamic: keywords
Dynamic: provides-extra
Dynamic: summary
